otoolbox/__init__.py
otoolbox/banner.txt
otoolbox/base.py
otoolbox/constants.py
otoolbox/environment.py
otoolbox/utils.py
otoolbox/addons/__init__.py
otoolbox/addons/addons/README.rst
otoolbox/addons/addons/__init__.py
otoolbox/addons/addons/config.py
otoolbox/addons/addons/constants.py
otoolbox/addons/docker/README.md
otoolbox/addons/docker/docker-compose.yml
otoolbox/addons/help/README.md
otoolbox/addons/help/WORKSPACE_README.md
otoolbox/addons/help/__init__.py
otoolbox/addons/logger/README.md
otoolbox/addons/logger/__init__.py
otoolbox/addons/repositories/README.md
otoolbox/addons/repositories/__init__.py
otoolbox/addons/repositories/config.py
otoolbox/addons/repositories/constants.py
otoolbox/addons/repositories/display.py
otoolbox/addons/repositories/git.py
otoolbox/addons/repositories/repositories.json
otoolbox/addons/ubuntu/README.md
otoolbox/addons/ubuntu/__init__.py
otoolbox/addons/ubuntu/bulk-add-repos.sh
otoolbox/addons/ubuntu/bulk-commit.sh
otoolbox/addons/ubuntu/bulk-pre-commit.sh
otoolbox/addons/ubuntu/bulk-push-shielded.sh
otoolbox/addons/ubuntu/ubuntu-install-apps.sh
otoolbox/addons/ubuntu/ubuntu-office-conf.sh
otoolbox/addons/vscode/README.md
otoolbox/addons/vscode/__init__.py
otoolbox/addons/vscode/code_cof.py
otoolbox/addons/vscode/dev_env.py
otoolbox/addons/vscode/requirements.txt
otoolbox/addons/vscode/workspace.json
otoolbox/addons/workspace/README.md
otoolbox/addons/workspace/__init__.py
otoolbox-0.2.4.dist-info/licenses/LICENSE.txt
otoolbox-0.2.4.dist-info/METADATA
otoolbox-0.2.4.dist-info/WHEEL
otoolbox-0.2.4.dist-info/entry_points.txt
otoolbox-0.2.4.dist-info/top_level.txt
otoolbox-0.2.4.dist-info/RECORD
