Metadata-Version: 2.4
Name: otoolbox
Version: 0.2.4
Summary: Utilities for Odoo from Odoonix
Home-page: https://odoonix.com/apps/otoolbox
Author: Odoonix
Author-email: info@odoonix.com
License: MIT
Platform: linux
Classifier: Development Status :: 4 - Beta
Classifier: Programming Language :: Python
Requires-Python: >=3.8
License-File: LICENSE.txt
Requires-Dist: importlib-metadata; python_version < "3.8"
Requires-Dist: rich>=13.9.4
Requires-Dist: typer
Requires-Dist: chevron
Requires-Dist: setuptools
Requires-Dist: dotenv
Requires-Dist: jsonpath_ng
Provides-Extra: testing
Requires-Dist: setuptools; extra == "testing"
Requires-Dist: pytest; extra == "testing"
Requires-Dist: pytest-cov; extra == "testing"
Dynamic: license-file
